CCankaoshouceDisanBufen20171220/README.md
CCankaoshouceDisanBufen20171220/__init__.py
CCankaoshouceDisanBufen20171220/__main__.py
CCankaoshouceDisanBufen20171220/file.epub
CCankaoshouceDisanBufen20171220/index.html
CCankaoshouceDisanBufen20171220/css/__init__.py
CCankaoshouceDisanBufen20171220/css/annotations.css
CCankaoshouceDisanBufen20171220/css/main.css
CCankaoshouceDisanBufen20171220/css/normalize.css
CCankaoshouceDisanBufen20171220/css/popup.css
CCankaoshouceDisanBufen20171220/font/__init__.py
CCankaoshouceDisanBufen20171220/font/fontello.eot
CCankaoshouceDisanBufen20171220/font/fontello.svg
CCankaoshouceDisanBufen20171220/font/fontello.ttf
CCankaoshouceDisanBufen20171220/font/fontello.woff
CCankaoshouceDisanBufen20171220/img/__init__.py
CCankaoshouceDisanBufen20171220/img/annotator-glyph-sprite.png
CCankaoshouceDisanBufen20171220/img/annotator-icon-sprite.png
CCankaoshouceDisanBufen20171220/img/apple-touch-icon.png
CCankaoshouceDisanBufen20171220/img/cancelfullscreen.png
CCankaoshouceDisanBufen20171220/img/close.png
CCankaoshouceDisanBufen20171220/img/fullscreen.png
CCankaoshouceDisanBufen20171220/img/loader.gif
CCankaoshouceDisanBufen20171220/img/menu-icon.png
CCankaoshouceDisanBufen20171220/img/save.png
CCankaoshouceDisanBufen20171220/img/saved.png
CCankaoshouceDisanBufen20171220/img/settings-s.png
CCankaoshouceDisanBufen20171220/img/settings.png
CCankaoshouceDisanBufen20171220/img/star.png
CCankaoshouceDisanBufen20171220/js/__init__.py
CCankaoshouceDisanBufen20171220/js/epub.js
CCankaoshouceDisanBufen20171220/js/epub.min.js
CCankaoshouceDisanBufen20171220/js/epub.min.map
CCankaoshouceDisanBufen20171220/js/hooks.min.js
CCankaoshouceDisanBufen20171220/js/hooks.min.map
CCankaoshouceDisanBufen20171220/js/reader.js
CCankaoshouceDisanBufen20171220/js/reader.js.map
CCankaoshouceDisanBufen20171220/js/reader.min.js
CCankaoshouceDisanBufen20171220/js/reader.min.map
CCankaoshouceDisanBufen20171220/js/hooks/__init__.py
c_cankaoshouce_disan_bufen_2017_12_20-2024.3.2.0.dist-info/METADATA
c_cankaoshouce_disan_bufen_2017_12_20-2024.3.2.0.dist-info/WHEEL
c_cankaoshouce_disan_bufen_2017_12_20-2024.3.2.0.dist-info/entry_points.txt
c_cankaoshouce_disan_bufen_2017_12_20-2024.3.2.0.dist-info/top_level.txt
c_cankaoshouce_disan_bufen_2017_12_20-2024.3.2.0.dist-info/RECORD
